oc_ldap_user_locker/__init__.py
oc_ldap_user_locker/__main__.py
oc_ldap_user_locker/locker.py
oc_ldap_user_locker/mailer.py
oc_ldap_user_locker-1.2.2.dist-info/LICENSE
oc_ldap_user_locker-1.2.2.dist-info/METADATA
oc_ldap_user_locker-1.2.2.dist-info/WHEEL
oc_ldap_user_locker-1.2.2.dist-info/top_level.txt
oc_ldap_user_locker-1.2.2.dist-info/RECORD
